aprsd_openweathermap_plugin/__init__.py
aprsd_openweathermap_plugin/time.py
aprsd_openweathermap_plugin/util.py
aprsd_openweathermap_plugin/weather.py
aprsd_openweathermap_plugin/conf/__init__.py
aprsd_openweathermap_plugin/conf/main.py
aprsd_openweathermap_plugin/conf/opts.py
aprsd_openweathermap_plugin-1.0.0.dist-info/licenses/LICENSE
aprsd_openweathermap_plugin-1.0.0.dist-info/METADATA
aprsd_openweathermap_plugin-1.0.0.dist-info/WHEEL
aprsd_openweathermap_plugin-1.0.0.dist-info/entry_points.txt
aprsd_openweathermap_plugin-1.0.0.dist-info/top_level.txt
aprsd_openweathermap_plugin-1.0.0.dist-info/RECORD
