Metadata-Version: 2.4
Name: aprsd-openweathermap-plugin
Version: 1.0.0
Summary: APRSD Plugin for OpenWeatherMap APIs
Author-email: "Walter A. Boring IV" <waboring@hemna.com>
Maintainer-email: "Walter A. Boring IV" <waboring@hemna.com>
License: 
Keywords: aprs,aprs-is,aprsd,aprsd-server,aprsd-client,aprsd-socket,aprsd-socket-server,aprsd-socket-client
Classifier: Development Status :: 5 - Production/Stable
Classifier: Environment :: Console
Classifier: Intended Audience :: Developers
Classifier: Intended Audience :: End Users/Desktop
Classifier: Intended Audience :: Information Technology
Classifier: Topic :: Communications :: Ham Radio
Classifier: Topic :: Internet
Classifier: Programming Language :: Python :: 3 :: Only
Classifier: Programming Language :: Python :: 3
Classifier: Programming Language :: Python :: 3.11
Requires-Python: >=3.11
License-File: LICENSE
Requires-Dist: aprsd>=4.2.0
Requires-Dist: oslo_config
Dynamic: license-file
